__init__.py
greetmsg.py
greetmsg-0.0.1.dist-info/LICENSE
greetmsg-0.0.1.dist-info/METADATA
greetmsg-0.0.1.dist-info/WHEEL
greetmsg-0.0.1.dist-info/top_level.txt
greetmsg-0.0.1.dist-info/RECORD
